LICENSE
MANIFEST.in
README.md
setup.py
flask_admin_ckeditor/__init__.py
flask_admin_ckeditor/view.py
flask_admin_ckeditor.egg-info/PKG-INFO
flask_admin_ckeditor.egg-info/SOURCES.txt
flask_admin_ckeditor.egg-info/dependency_links.txt
flask_admin_ckeditor.egg-info/requires.txt
flask_admin_ckeditor.egg-info/top_level.txt
flask_admin_ckeditor/ckeditor/__init__.py
flask_admin_ckeditor/ckeditor/fields.py
flask_admin_ckeditor/ckeditor/upload/__init__.py
flask_admin_ckeditor/ckeditor/upload/filename.py
flask_admin_ckeditor/ckeditor/upload/response.py
flask_admin_ckeditor/ckeditor/upload/uploader.py
flask_admin_ckeditor/markdown/__init__.py